serp_forge/__init__.py
serp_forge/cli.py
serp_forge/config.py
serp_forge/serper/__init__.py
serp_forge/serper/client.py
serp_forge/serper/core.py
serp_forge/serper/models.py
serp_forge/serper/scraper.py
serp_forge/utils/__init__.py
serp_forge/utils/logging.py
serp_forge-1.0.0.dist-info/licenses/LICENSE
serp_forge-1.0.0.dist-info/METADATA
serp_forge-1.0.0.dist-info/WHEEL
serp_forge-1.0.0.dist-info/entry_points.txt
serp_forge-1.0.0.dist-info/top_level.txt
serp_forge-1.0.0.dist-info/RECORD
