Metadata-Version: 2.4
Name: serp-forge
Version: 1.0.0
Summary: A powerful web scraping toolkit for SERP data extraction and analysis
Home-page: https://github.com/vishalm/serp-forge
Author: Serp Forge Team
Author-email: Vishal Mishra <vishal.mishra@example.com>
Maintainer-email: Vishal Mishra <vishal.mishra@example.com>
License: MIT
Project-URL: Homepage, https://github.com/vishalm/serp-forge
Project-URL: Documentation, https://github.com/vishalm/serp-forge#readme
Project-URL: Repository, https://github.com/vishalm/serp-forge
Project-URL: Bug Tracker, https://github.com/vishalm/serp-forge/issues
Project-URL: Release Notes, https://github.com/vishalm/serp-forge/releases
Project-URL: Download, https://pypi.org/project/serp-forge/
Keywords: web-scraping,serp,search-engine,data-extraction,api-client
Classifier: Development Status :: 4 - Beta
Classifier: Intended Audience :: Developers
Classifier: License :: OSI Approved :: MIT License
Classifier: Operating System :: OS Independent
Classifier: Programming Language :: Python :: 3
Classifier: Programming Language :: Python :: 3.9
Classifier: Programming Language :: Python :: 3.10
Classifier: Programming Language :: Python :: 3.11
Classifier: Programming Language :: Python :: 3.12
Classifier: Topic :: Internet :: WWW/HTTP :: Dynamic Content
Classifier: Topic :: Software Development :: Libraries :: Python Modules
Classifier: Topic :: Text Processing :: Markup :: HTML
Requires-Python: >=3.8
License-File: LICENSE
Requires-Dist: requests>=2.25.0
Requires-Dist: beautifulsoup4>=4.9.0
Requires-Dist: lxml>=4.6.0
Requires-Dist: pydantic>=2.0.0
Requires-Dist: pyyaml>=6.0
Requires-Dist: click>=8.0.0
Requires-Dist: rich>=12.0.0
Requires-Dist: aiohttp>=3.8.0
Requires-Dist: asyncio-throttle>=1.0.0
Requires-Dist: tenacity>=8.0.0
Provides-Extra: dev
Requires-Dist: pytest>=7.0.0; extra == "dev"
Requires-Dist: pytest-cov>=4.0.0; extra == "dev"
Requires-Dist: pytest-asyncio>=0.21.0; extra == "dev"
Requires-Dist: pytest-mock>=3.10.0; extra == "dev"
Requires-Dist: black>=22.0.0; extra == "dev"
Requires-Dist: isort>=5.10.0; extra == "dev"
Requires-Dist: flake8>=5.0.0; extra == "dev"
Requires-Dist: mypy>=1.0.0; extra == "dev"
Requires-Dist: pre-commit>=2.20.0; extra == "dev"
Provides-Extra: docs
Requires-Dist: sphinx>=5.0.0; extra == "docs"
Requires-Dist: sphinx-rtd-theme>=1.0.0; extra == "docs"
Requires-Dist: myst-parser>=0.18.0; extra == "docs"
Provides-Extra: test
Requires-Dist: pytest>=7.0.0; extra == "test"
Requires-Dist: pytest-cov>=4.0.0; extra == "test"
Requires-Dist: pytest-asyncio>=0.21.0; extra == "test"
Requires-Dist: pytest-mock>=3.10.0; extra == "test"
Requires-Dist: responses>=0.22.0; extra == "test"
Requires-Dist: freezegun>=1.2.0; extra == "test"
Dynamic: author
Dynamic: home-page
Dynamic: license-file
Dynamic: requires-python
